LICENSE
MANIFEST.in
README.md
setup.py
dash_bio_utils/__init__.py
dash_bio_utils.egg-info/PKG-INFO
dash_bio_utils.egg-info/SOURCES.txt
dash_bio_utils.egg-info/dependency_links.txt
dash_bio_utils.egg-info/top_level.txt