Metadata-Version: 2.1
Name: dash-bio-utils
Version: 1.0.0
Summary: Simple parsing tools that supplement dash-bio.
Home-page: http://github.com/plotly/dash-bio-utils
Author: The Plotly Team
Author-email: dashbio@plot.ly
License: UNKNOWN
Platform: UNKNOWN
Classifier: Programming Language :: Python :: 3
Classifier: License :: OSI Approved :: MIT License
Classifier: Operating System :: OS Independent
